aesthetic_ascii/31-synthwave-sun-waves-electronic-sky.jpg
aesthetic_ascii/RobotoMono-VariableFont_wght.ttf
aesthetic_ascii/__init__.py
aesthetic_ascii/city-5848267_1920.jpg
aesthetic_ascii/synthesize.py
aesthetic_ascii/wallpaperuse.com-outrun-wallpaper-76590.png
aesthetic_ascii/wallpaperuse.com-outrun-wallpaper-76592.png
aesthetic_ascii/wallpaperuse.com-retro-wallpaper-hd-999925.png
aesthetic_ascii/wallpaperuse.com-synthwave-wallpaper-1003075.jpg
aesthetic_ascii/wallpaperuse.com-wallpapers-retro-803078.jpg
aesthetic_ascii-0.0.2.dist-info/LICENSE
aesthetic_ascii-0.0.2.dist-info/METADATA
aesthetic_ascii-0.0.2.dist-info/WHEEL
aesthetic_ascii-0.0.2.dist-info/top_level.txt
aesthetic_ascii-0.0.2.dist-info/RECORD
