Metadata-Version: 2.1
Name: aesthetic-ascii
Version: 0.0.2
Summary: For generating A E S T H E T I C ascii art
Home-page: https://github.com/jamescalam/aesthetic_ascii
Author: James Briggs
Author-email: jamescalam94@gmail.com
License: UNKNOWN
Platform: UNKNOWN
Classifier: Programming Language :: Python :: 3
Classifier: License :: OSI Approved :: MIT License
Classifier: Operating System :: OS Independent
Requires-Python: >=3.7
